Metadata-Version: 2.1
Name: example-pkg-shan
Version: 1.0.0
Summary: A small example package
Home-page: UNKNOWN
Author: Example Author
Author-email: author@example.com
License: UNKNOWN
Platform: UNKNOWN
Classifier: Programming Language :: Python :: 3
Classifier: License :: OSI Approved :: MIT License
Classifier: Operating System :: OS Independent
